dice_cli/__init__.py
dice_cli/_date.py
dice_cli/cache.py
dice_cli/dicectl.py
dice_cli/logger.py
dice_cli/main.py
dice_cli/py.typed
dice_cli/_io/__init__.py
dice_cli/_io/_csv.py
dice_cli/_io/_remote.py
dice_cli/admin/__init__.py
dice_cli/admin/_print_unused_id_ranges.py
dice_cli/admin/_print_used_id_ranges.py
dice_cli/admin/_scan_groups_and_users.py
dice_cli/admin/deploy/__init__.py
dice_cli/admin/deploy/_hdfs_mount.py
dice_cli/admin/investigate/__init__.py
dice_cli/admin/report/__init__.py
dice_cli/admin/report/_consistency_check_grid.py
dice_cli/admin/report/_dns.py
dice_cli/admin/report/_inventory.py
dice_cli/admin/report/_network.py
dice_cli/admin/report/_resources.py
dice_cli/admin/report/_storage.py
dice_cli/benchmark/__init__.py
dice_cli/check/__init__.py
dice_cli/check/_environment.py
dice_cli/docs/__init__.py
dice_cli/fs/__init__.py
dice_cli/fs/_copy_from_local.py
dice_cli/info/__init__.py
dice_cli/job/__init__.py
dice_cli/migrate/__init__.py
dice_cli/restore/__init__.py
dice_cli/sync/__init__.py
dice_cli-2025.3.1.dist-info/METADATA
dice_cli-2025.3.1.dist-info/WHEEL
dice_cli-2025.3.1.dist-info/entry_points.txt
dice_cli-2025.3.1.dist-info/licenses/LICENSE
dice_cli-2025.3.1.dist-info/RECORD
