Metadata-Version: 2.4
Name: dice_cli
Version: 2025.3.1
Summary: Command-line interface for DICE
Project-URL: homepage, https://github.com/uobdic/dice-cli
Author-email: Luke Kreczko <kreczko@cern.ch>
Maintainer-email: The UoB DICE team <lcg-admin@bristol.ac.uk>
License: BSD 3-Clause License
License-File: LICENSE
Classifier: Development Status :: 1 - Planning
Classifier: Intended Audience :: Developers
Classifier: Intended Audience :: Science/Research
Classifier: License :: OSI Approved :: BSD License
Classifier: Operating System :: OS Independent
Classifier: Programming Language :: Python
Classifier: Programming Language :: Python :: 3
Classifier: Programming Language :: Python :: 3.9
Classifier: Programming Language :: Python :: 3.10
Classifier: Topic :: Scientific/Engineering
Requires-Python: >=3.11
Requires-Dist: colorama>=0.4.0
Requires-Dist: dice-lib>=2024.04.01
Requires-Dist: diskcache>=5.4.0
Requires-Dist: htcondor>=9.0.0
Requires-Dist: plumbum>=1.7.2
Requires-Dist: prettytable>=3.2.0
Requires-Dist: requests<3.0.0
Requires-Dist: rich>=10.12.0
Requires-Dist: shellingham>=1.4.0
Requires-Dist: tabulate>=0.8.9
Requires-Dist: tqdm<5.0.0
Requires-Dist: typer>=0.4.0
Requires-Dist: typing-extensions>=3.7
Provides-Extra: admin
Requires-Dist: python-nmap>=0.7.1; extra == 'admin'
Provides-Extra: dev
Requires-Dist: pytest>=6; extra == 'dev'
Provides-Extra: docs
Requires-Dist: myst-parser>=0.13; extra == 'docs'
Requires-Dist: sphinx-book-theme>=0.1.0; extra == 'docs'
Requires-Dist: sphinx-copybutton; extra == 'docs'
Requires-Dist: sphinx~=7.0; extra == 'docs'
Provides-Extra: test
Requires-Dist: pytest>=6; extra == 'test'
